investingfetcher/__init__.py
investingfetcher/equity.py
investingfetcher/fetchers/EquityFetcher.py
investingfetcher/fetchers/Fetcher.py
investingfetcher/fetchers/FinancialFetcher.py
investingfetcher/fetchers/NewsFetcher.py
investingfetcher/fetchers/__init__.py
investingfetcher/parsers/Financials/BalanceSheet.py
investingfetcher/parsers/Financials/CashFlow.py
investingfetcher/parsers/Financials/Dividends.py
investingfetcher/parsers/Financials/Earnings.py
investingfetcher/parsers/Financials/IncomeStatement.py
investingfetcher/parsers/Financials/Ratios.py
investingfetcher/parsers/Financials/__init__.py
investingfetcher/parsers/News/LinkParsers.py
investingfetcher/parsers/News/NewsParser.py
investingfetcher/parsers/News/__init__.py
investingfetcher/parsers/Parser.py
investingfetcher/parsers/__init__.py
investingfetcher-0.1.0.dist-info/METADATA
investingfetcher-0.1.0.dist-info/WHEEL
investingfetcher-0.1.0.dist-info/RECORD
