Metadata-Version: 2.1
Name: investingfetcher
Version: 0.1.0
Summary: 
Author: Iaroslav Plaksin
Author-email: gotaatr@gmail.com
Requires-Python: >=3.9,<4.0
Classifier: Programming Language :: Python :: 3
Classifier: Programming Language :: Python :: 3.9
Classifier: Programming Language :: Python :: 3.10
Classifier: Programming Language :: Python :: 3.11
Requires-Dist: aiohttp (>=3.8.5,<4.0.0)
Requires-Dist: pandas (>=2.1.0,<3.0.0)
Requires-Dist: pylint (>=2.17.5,<3.0.0)
Requires-Dist: zenrows (>=1.3.1,<2.0.0)
